Workbook

Sheet Sheet17
A1: 📝 Complete Business Workflow Summary (17 Steps)
A2: Step No. | B2: Step Name | C2: Customer-Facing Trigger/Medium
A3: Part 1: Order, Logistics, and Financial Setup
A4: 1 | B4: Customer Order via Chat | C4: Chat (WhatsApp, etc.)
A5: 2 | B5: Invoice Process & Email to Customer | C5: Internal System Check / Email (Invoice Dispatch)
A6: 3 | B6: Purchase Order (PO) and Supplier Communication | C6: Chat (WhatsApp, etc.)
A7: 4 | B7: Expiry Stock Alert System | C7: Internal System Check (Time/Condition-based)
A8: 5 | B8: Daily Dispatch and Customer Notification | C8: Internal System Check / Email (Dispatch Confirmation)
A9: 6 | B9: Delivery Status Monitoring and Alert | C9: Internal System Check (Daily 6 PM Trigger)
A10: 7 | B10: Delivery Confirmation and Final Customer Notification | C10: Form (Delivery Man Submission) / Email (Delivery Confirmation)
A11: Part 2: Inventory, Finance, and Reporting
A12: 8 | B12: Sales Analysis and Stock Register Enrichment | C12: Internal System Check
A13: 9 | B13: Automated Reorder and Purchase Order Generation | C13: Internal System Check (ROL Condition Met)
A14: 10 | B14: Dead Stock and Slow-Moving Inventory Alert | C14: Internal System Check (Weekly/Monthly Trigger)
A15: 11 | B15: Payment Register Reconciliation and Due Date Setting | C15: Internal System Check (Daily 11 PM Trigger)
A16: 12 | B16: Overdue Payment Alert and Follow-up | C16: Internal System Check / Email (Overdue Reminder)
A17: 13 | B17: Monthly Financial Reporting (P&L and Stock Valuation) | C17: Internal System Check (Monthly Trigger)
A18: Part 3: Sales and Customer Relationship Management (CRM)
A19: 14 | B19: New Product Launch Communication | C19: Internal System Check / Email (Launch Alert)
A20: 15 | B20: Proactive Clearance Discount Campaign | C20: Internal System Check / Email (Discount Offer)
A21: 16 | B21: Personalized Customer Retention Campaign | C21: Internal System Check / Email (Personalized Offer)
A22: 17 | B22: Automated Customer Feedback Loop | C22: Form (Customer Submission) / Email (Confirmation & Reply)
A24: Internal System Check refers to processes triggered automatically by the system itself (e.g., at a specific time, like 6:00 PM, or when a condition is met, like stock falling below 500).

Sheet Customer Feedback
A1: Timestamp | B1: Customer Name | C1: WhatsApp Number | D1: Email | E1: Order ID | F1: Feedback Category | G1: Feedback Message | H1: Consent
A2: 45989.717 | B2: Asif | C2: 0343-4379809 | D2: shahfaisal1234@gmail.com | E2: ORD-123456789 | F2: Delivery issue | G2: I am not satisfied with the delivery timeline | H2: Email

Sheet New Product Campaign
A1: Timestamp | B1: Product ID | C1: Product Name | D1: Category | E1: Price | F1: Product Description
A2: 45990.87 | B2: 5 | C2: Nestle Juice | D2: Juices | E2: 100 | F2: Experience the tropical fusion of real mango and tangy passionfruit in Nestlé's new juice, packed with natural Vitamin C and absolutely no added sugar

Sheet Expense Record
A1: Timestamp | B1: Expense Type | C1: Description | D1: Amount
A2: 2025-12-02T12:15:02.044-05:00 | B2: Fuel | C2: Bike | D2: 1000
A3: 2025-11-02T12:15:02.044-05:00 | B3: Fuel | C3: Bike | D3: 1000

Sheet Delivery Status
A1: Timestamp | B1: Order ID | C1: Delivery Status | D1: Amount Paid | E1: Payment Method
A2: 45994.003 | B2: Ord-1764684181323 | C2: Delivered | D2: 10000

Sheet Supplier Infomation
A1: company_name | B1: contact_number | C1: email | D1: contact_person | E1: product | F1: product_id | G1: product_name | H1: size | I1: category
A2: Nestle Water Pvt. Ltd. | B2: 923434379809 | C2: shahfaisal1234@gmail.com | D2: Faisal Mehmood | E2: nestle_water | F2: 1 | G2: Nestle Water Pure Life | H2: 500 ml | I2: water
F3: 2 | G3: Nestle Water Pure Life | H3: 1500 ml | I3: water
F4: 3 | G4: Nestle Water Pure Life | H4: 5 Litre | I4: water
F5: 4 | G5: Nestle Water Pure Life | H5: 19 Litre | I5: water

Sheet Purchase Order
A1: timestamp | B1: product_id | C1: product_name | D1: size | E1: category | F1: qty_order
A2: 2025-12-02T10:16:41.243-05:00 | B2: 1 | C2: Nestle Water Pure Life | D2: 500 ml | E2: water | F2: 500
A3: 2025-12-02T14:55:14.257-05:00 | B3: 1 | C3: Nestle Water Pure Life | D3: 500 ml | E3: water | F3: 500

Sheet Stock Received
A1: timestamp | B1: invoice_no | C1: product_id | D1: product_name | E1: size | F1: category | G1: qty_recieved | H1: cost_price | I1: total_cost | J1: expiry_date | K1: expairy_days_remaining | L1: expiry_alert_sent
A2: 2025-11-18T12:15:02.044-05:00 | B2: Inv-1764275633816 | C2: 1 | D2: Nestle Water Pure Life | E2: 500 ml | F2: water | G2: 1000 | H2: 50 | I2: =H2*G2 -> 50000 | J2: 18-11-2026 | K2: =DATE(RIGHT(J2,4), MID(J2,4,2), LEFT(J2,2)) - TODAY() -> 348 | L2: No
A3: 2025-11-18T12:15:02.044-05:00 | B3: Inv-1764275633825 | C3: 2 | D3: Nestle Water Pure Life | E3: 1500 ml | F3: water | G3: 1000 | H3: 100 | I3: =H3*G3 -> 100000 | J3: 18-11-2026 | K3: =DATE(RIGHT(J3,4), MID(J3,4,2), LEFT(J3,2)) - TODAY() -> 348 | L3: No
A4: 2025-11-18T12:15:02.044-05:00 | B4: Inv-1764275633845 | C4: 3 | D4: Nestle Water Pure Life | E4: 5 Litre | F4: water | G4: 1000 | H4: 200 | I4: =H4*G4 -> 200000 | J4: 18-11-2026 | K4: =DATE(RIGHT(J4,4), MID(J4,4,2), LEFT(J4,2)) - TODAY() -> 348 | L4: No
A5: 2025-11-18T12:15:02.044-05:00 | B5: Inv-1764275633860 | C5: 4 | D5: Nestle Water Pure Life | E5: 19 Litre | F5: water | G5: 1000 | H5: 500 | I5: =H5*G5 -> 500000 | J5: 18-11-2026 | K5: =DATE(RIGHT(J5,4), MID(J5,4,2), LEFT(J5,2)) - TODAY() -> 348 | L5: No
A6: 2025-12-02T12:15:02.044-05:00 | B6: INV-1764695702045 | C6: 1 | D6: Nestle Water Pure Life | E6: 500 ml | F6: water | G6: 500 | H6: 50 | I6: =H6*G6 -> 25000 | J6: 23-12-2025 | K6: =DATE(RIGHT(J6,4), MID(J6,4,2), LEFT(J6,2)) - TODAY() -> 18 | L6: Yes

Sheet Purchase Register
A1: Sr | B1: product_id | C1: product_name | D1: size | E1: category | F1: qty_received | G1: cost_price_per_unit | H1: sale_price_per_unit | I1: total_cost
A2: 1 | B2: 1 | C2: Nestle Water Pure Life | D2: 500 ml | E2: water | F2: =SUMIF('Stock Received'!C:C, B2, 'Stock Received'!G:G) -> 1500 | G2: 50 | H2: 100 | I2: =F2*G2 -> 75000
A3: 2 | B3: 2 | C3: Nestle Water Pure Life | D3: 1500 ml | E3: water | F3: =SUMIF('Stock Received'!C:C, B3, 'Stock Received'!G:G) -> 1000 | G3: 100 | H3: 200 | I3: =F3*G3 -> 100000
A4: 3 | B4: 3 | C4: Nestle Water Pure Life | D4: 5 Litre | E4: water | F4: =SUMIF('Stock Received'!C:C, B4, 'Stock Received'!G:G) -> 1000 | G4: 200 | H4: 400 | I4: =F4*G4 -> 200000
A5: 4 | B5: 4 | C5: Nestle Water Pure Life | D5: 19 Litre | E5: water | F5: =SUMIF('Stock Received'!C:C, B5, 'Stock Received'!G:G) -> 1000 | G5: 500 | H5: 1000 | I5: =F5*G5 -> 500000

Sheet Sales Register
A1: sr # | B1: product_id | C1: product_name | D1: size | E1: category | F1: sale | G1: sale_price | H1: total_sale
A2: 1 | B2: 1 | C2: =VLOOKUP(B2, 'Purchase Register'!B:F, 2, FALSE) -> Nestle Water Pure Life | D2: =VLOOKUP(B2, 'Purchase Register'!B:F, 3, FALSE) -> 500 ml | E2: =VLOOKUP(B2, 'Purchase Register'!B:H, 4, FALSE) -> water | F2: =SUMIF('Customer Order'!B:B, B2, 'Customer Order'!F:F) -> 100 | G2: ='Purchase Register'!H2 -> 100 | H2: =G2*F2 -> 10000
A3: 2 | B3: 2 | C3: =VLOOKUP(B3, 'Purchase Register'!B:F, 2, FALSE) -> Nestle Water Pure Life | D3: =VLOOKUP(B3, 'Purchase Register'!B:F, 3, FALSE) -> 1500 ml | E3: =VLOOKUP(B3, 'Purchase Register'!B:H, 4, FALSE) -> water | F3: =SUMIF('Customer Order'!B:B, B3, 'Customer Order'!F:F) -> 0 | G3: ='Purchase Register'!H3 -> 200 | H3: =G3*F3 -> 0
A4: 3 | B4: 3 | C4: =VLOOKUP(B4, 'Purchase Register'!B:F, 2, FALSE) -> Nestle Water Pure Life | D4: =VLOOKUP(B4, 'Purchase Register'!B:F, 3, FALSE) -> 5 Litre | E4: =VLOOKUP(B4, 'Purchase Register'!B:H, 4, FALSE) -> water | F4: =SUMIF('Customer Order'!B:B, B4, 'Customer Order'!F:F) -> 0 | G4: ='Purchase Register'!H4 -> 400 | H4: =G4*F4 -> 0
A5: 4 | B5: 4 | C5: =VLOOKUP(B5, 'Purchase Register'!B:F, 2, FALSE) -> Nestle Water Pure Life | D5: =VLOOKUP(B5, 'Purchase Register'!B:F, 3, FALSE) -> 19 Litre | E5: =VLOOKUP(B5, 'Purchase Register'!B:H, 4, FALSE) -> water | F5: =SUMIF('Customer Order'!B:B, B5, 'Customer Order'!F:F) -> 0 | G5: ='Purchase Register'!H5 -> 1000 | H5: =G5*F5 -> 0

Sheet Stock Register
A1: product_id | B1: product_name | C1: size | D1: category | E1: purchase_stock | F1: sale_stock | G1: current_stock | H1: cost_price | I1: sale_price | J1: total_purchase | K1: total_sale | L1: status | M1: reorder_level | N1: need_to_reorder | O1: last_30_days_sale | P1: days_since_last_sale
A2: 1 | B2: =VLOOKUP(A2, 'Purchase Register'!B:E, 2, FALSE) -> Nestle Water Pure Life | C2: =VLOOKUP(A2, 'Purchase Register'!B:E, 3, FALSE) -> 500 ml | D2: =VLOOKUP(B2, 'Purchase Register'!C:F, 3, FALSE) -> water | E2: =VLOOKUP(C2, 'Purchase Register'!D:G, 3, FALSE) -> 1500 | F2: =VLOOKUP(A2, 'Sales Register'!A:G, 6, FALSE) -> 100 | G2: =E2-F2 -> 1400 | H2: =VLOOKUP(A2, 'Purchase Register'!B:I, 6, FALSE) -> 50 | I2: =VLOOKUP(A2, 'Purchase Register'!B:I, 7, FALSE) -> 100 | J2: =E2*H2 -> 75000 | K2: =F2*I2 -> 10000 | L2: =IF(G2=0,"Not Available",IF(G2<=10,"Low Stock","Available")) -> Available | M2: 500 | N2: =IF(G2<=M2,"Yes","No") -> No | O2: 100 | P2: 0
A3: 2 | B3: =VLOOKUP(A3, 'Purchase Register'!B:E, 2, FALSE) -> Nestle Water Pure Life | C3: =VLOOKUP(A3, 'Purchase Register'!B:E, 3, FALSE) -> 1500 ml | D3: =VLOOKUP(B3, 'Purchase Register'!C:F, 3, FALSE) -> water | E3: =VLOOKUP(C3, 'Purchase Register'!D:G, 3, FALSE) -> 1000 | F3: =VLOOKUP(A3, 'Sales Register'!A:G, 6, FALSE) -> 0 | G3: =E3-F3 -> 1000 | H3: =VLOOKUP(A3, 'Purchase Register'!B:I, 6, FALSE) -> 100 | I3: =VLOOKUP(A3, 'Purchase Register'!B:I, 7, FALSE) -> 200 | J3: =E3*H3 -> 100000 | K3: =F3*I3 -> 0 | L3: =IF(G3=0,"Not Available",IF(G3<=10,"Low Stock","Available")) -> Available | M3: 500 | N3: =IF(G3<=M3,"Yes","No") -> No
A4: 3 | B4: =VLOOKUP(A4, 'Purchase Register'!B:E, 2, FALSE) -> Nestle Water Pure Life | C4: =VLOOKUP(A4, 'Purchase Register'!B:E, 3, FALSE) -> 5 Litre | D4: =VLOOKUP(B4, 'Purchase Register'!C:F, 3, FALSE) -> water | E4: =VLOOKUP(C4, 'Purchase Register'!D:G, 3, FALSE) -> 1000 | F4: =VLOOKUP(A4, 'Sales Register'!A:G, 6, FALSE) -> 0 | G4: =E4-F4 -> 1000 | H4: =VLOOKUP(A4, 'Purchase Register'!B:I, 6, FALSE) -> 200 | I4: =VLOOKUP(A4, 'Purchase Register'!B:I, 7, FALSE) -> 400 | J4: =E4*H4 -> 200000 | K4: =F4*I4 -> 0 | L4: =IF(G4=0,"Not Available",IF(G4<=10,"Low Stock","Available")) -> Available | M4: 500 | N4: =IF(G4<=M4,"Yes","No") -> No
A5: 4 | B5: =VLOOKUP(A5, 'Purchase Register'!B:E, 2, FALSE) -> Nestle Water Pure Life | C5: =VLOOKUP(A5, 'Purchase Register'!B:E, 3, FALSE) -> 19 Litre | D5: =VLOOKUP(B5, 'Purchase Register'!C:F, 3, FALSE) -> water | E5: =VLOOKUP(C5, 'Purchase Register'!D:G, 3, FALSE) -> 1000 | F5: =VLOOKUP(A5, 'Sales Register'!A:G, 6, FALSE) -> 0 | G5: =E5-F5 -> 1000 | H5: =VLOOKUP(A5, 'Purchase Register'!B:I, 6, FALSE) -> 500 | I5: =VLOOKUP(A5, 'Purchase Register'!B:I, 7, FALSE) -> 1000 | J5: =E5*H5 -> 500000 | K5: =F5*I5 -> 0 | L5: =IF(G5=0,"Not Available",IF(G5<=10,"Low Stock","Available")) -> Available | M5: 500 | N5: =IF(G5<=M5,"Yes","No") -> No

Sheet Customer Order
A1: timestamp | B1: product_id | C1: product_name | D1: size | E1: category | F1: quntity | G1: price | H1: total_price | I1: order_id | J1: customer_name | K1: whatsapp_number | L1: email | M1: address | N1: landmark | O1: payment_method | P1: delivery_time_preference | Q1: status | R1: description
A2: 2025-11-18T12:15:02.044-05:00 | B2: 1 | C2: Nestle Water Pure Life | D2: 500 ml | E2: water | F2: 100 | G2: 100 | H2: 10000 | I2: Ord-1764684181323 | J2: Faisal Mahmood | K2: 923434379809 | L2: shahfaisal1234@gmail.com | M2: Multan | N2: Faisal Mosque | O2: Pending | P2: Afternoon | Q2: Delivered | R2: Order accepted (in stock)

Sheet Dispatch
A1: order_id | B1: dispatch_date | C1: delivery_person | D1: delivery_contact | E1: customer_name | F1: customer_phone | G1: customer_email | H1: delivery_deadline | I1: current_status | J1: alert_sent
A2: Ord-1764684181323 | B2: 45993 | C2: Salesman Name | D2: 311111111 | E2: Faisal Mahmood | F2: 923434379809 | G2: shahfaisal1234@gmail.com | H2: 45994 | I2: Delivered | J2: YES

Sheet Invoice
A1: invoice no | B1: date | C1: customer_name | D1: whatsapp_no | E1: address | F1: product_name | G1: size | H1: quntity | I1: price | J1: total_amount | K1: status
A2: INV-1764687120673 | B2: 2025-11-18T00:00:00.000-05:00 | C2: Faisal Mahmood | D2: 923434379809 | E2: Multan | F2: Nestle Water Pure Life | G2: 500 ml | H2: 100 | I2: 100 | J2: 10000

Sheet Payment
A1: order_id | B1: customer_name | C1: customer_email | D1: payment_status | E1: amount_paid | F1: balance | G1: due_date
A2: Ord-1764684181323 | B2: Faisal Mahmood | C2: shahfaisal1234@gmail.com | D2: Pending | E2: 0 | F2: 10000 | G2: 45669
A3: Ord-1764684181323 | B3: Faisal Mahmood | C3: shahfaisal1234@gmail.com | D3: Paid | E3: 10000 | F3: 0 | G3: Cash Paid
A4: Ord-1764684181323 | B4: Faisal Mahmood | C4: shahfaisal1234@gmail.com | D4: Paid | E4: 10000 | F4: 0 | G4: Cash Paid
A5: Ord-1764684181323 | B5: Faisal Mahmood | C5: shahfaisal1234@gmail.com | D5: Paid | E5: 10000 | F5: 0 | G5: Cash Paid
A6: Ord-1764684181323 | B6: Faisal Mahmood | C6: shahfaisal1234@gmail.com | D6: Pending | E6: 10000 | F6: 0 | G6: 46009

Sheet PL
A1: Date | B1: Total Revenue | C1: Total CGOS | D1: Gross Profit | E1: Total Expense | F1: Net Profit / Loss | G1: Current Stock Total Value
A2: 2025-12-03T06:22:51.592-05:00 | B2: 10000 | C2: 850000 | D2: -840000 | E2: 1000 | F2: -841000 | G2: 870000

Sheet Campaign Logs New Product
A1: Timestamp | B1: Customer Name | C1: Customer Email | D1: Product ID | E1: Product Name | F1: Category | G1: Description | H1: Status
A2: 2025-12-03T08:16:56.042-05:00 | B2: there | C2: shareknow29@gmail.com | D2: 5 | E2: 150 | F2: Juices | G2: Experience the tropical fusion of real mango and tangy passionfruit in Nestlé's new juice, packed with natural Vitamin C and absolutely no added sugar | H2: Sent
A3: 2025-12-03T08:18:31.832-05:00 | B3: there | C3: shareknow29@gmail.com | D3: 5 | E3: 150 | F3: Juices | G3: Experience the tropical fusion of real mango and tangy passionfruit in Nestlé's new juice, packed with natural Vitamin C and absolutely no added sugar | H3: Sent
A4: 2025-12-03T11:10:46.566-05:00 | B4: there | C4: shareknow29@gmail.com | D4: 5 | E4: Nestle Juices | F4: Juices | G4: Experience the tropical fusion of real mango and tangy passionfruit in Nestlé's new juice, packed with natural Vitamin C and absolutely no added sugar | H4: Sent
A5: 2025-12-03T11:20:40.867-05:00 | B5: there | C5: shahfaisal1234@gmail.com | D5: 5 | E5: Nestle Juice | F5: Juices | G5: Experience the tropical fusion of real mango and tangy passionfruit in Nestlé's new juice, packed with natural Vitamin C and absolutely no added sugar | H5: Sent
A6: 2025-12-03T11:22:52.874-05:00 | B6: Faisal Mahmood | C6: shahfaisal1234@gmail.com | D6: 5 | E6: Nestle Juice | F6: Juices | G6: Experience the tropical fusion of real mango and tangy passionfruit in Nestlé's new juice, packed with natural Vitamin C and absolutely no added sugar | H6: Sent

Sheet Slow Moving Stock Campaign 
A1: Timestamp | B1: Customer Name | C1: Customer Email | D1: Product ID | E1: Product Name | F1: Size | G1: Original_Price | H1: Discounted Price | I1: Offer Message | J1: Status
A2: 2025-12-03T12:26:01.461-05:00 | B2: Faisal Mahmood | C2: shahfaisal1234@gmail.com | D2: 2 | E2: Nestle Water Pure Life | G2: 200 | H2: 160 | I2: Special Offer! Nestle Water Pure Life (1500 ml) is available at Rs 160 instead of Rs 200! Limited time only. | J2: "Sent"
A3: 2025-12-03T12:26:01.468-05:00 | B3: Faisal Mahmood | C3: shahfaisal1234@gmail.com | D3: 3 | E3: Nestle Water Pure Life | G3: 400 | H3: 320 | I3: Special Offer! Nestle Water Pure Life (5 Litre) is available at Rs 320 instead of Rs 400! Limited time only. | J3: "Sent"
A4: 2025-12-03T12:26:01.471-05:00 | B4: Faisal Mahmood | C4: shahfaisal1234@gmail.com | D4: 4 | E4: Nestle Water Pure Life | G4: 1000 | H4: 800 | I4: Special Offer! Nestle Water Pure Life (19 Litre) is available at Rs 800 instead of Rs 1000! Limited time only. | J4: "Sent"
A5: 2025-12-03T12:27:51.383-05:00 | B5: Faisal Mahmood | C5: shahfaisal1234@gmail.com | D5: 2 | E5: Nestle Water Pure Life | F5: 1500 ml | G5: 200 | H5: 160 | I5: Special Offer! Nestle Water Pure Life (1500 ml) is available at Rs 160 instead of Rs 200! Limited time only. | J5: "Sent"
A6: 2025-12-03T12:27:51.392-05:00 | B6: Faisal Mahmood | C6: shahfaisal1234@gmail.com | D6: 3 | E6: Nestle Water Pure Life | F6: 5 Litre | G6: 400 | H6: 320 | I6: Special Offer! Nestle Water Pure Life (5 Litre) is available at Rs 320 instead of Rs 400! Limited time only. | J6: "Sent"
A7: 2025-12-03T12:27:51.395-05:00 | B7: Faisal Mahmood | C7: shahfaisal1234@gmail.com | D7: 4 | E7: Nestle Water Pure Life | F7: 19 Litre | G7: 1000 | H7: 800 | I7: Special Offer! Nestle Water Pure Life (19 Litre) is available at Rs 800 instead of Rs 1000! Limited time only. | J7: "Sent"

Sheet Personalized Campaign Logs
A1: Timestamp | B1: OrderID | C1: Name | D1: Email | E1: Subject | F1: EmailBody | G1: CouponCode | H1: DiscountPercent | I1: UrgencyText
A2: 2025-12-03T13:38:10.391-05:00 | B2: Ord-1764684181323 | C2: Faisal Mahmood | D2: shahfaisal1234@gmail.com | E2: Special offer for Faisal Mahmood | F2: <br><br>We have a special offer for you! Use the code <b>SAVE20</b> at checkout to save <b>20%</b> on your next purchase.<br><br> Hurry, this offer expires soon!<br> | G2: SAVE20 | H2: 20 | I2: Hurry, this offer expires soon!

Sheet Feedback Logs
A1: Acknowledgment Sent | B1: Status | C1: Processed Time
A2: SENT | B2: UNREAD | C2: 45989.717
A3: SENT | B3: UNREAD | C3: 45989.717
