Workbook

Sheet Company Infomation
A1: company_name | B1: contact_number | C1: email | D1: contact_person | E1: product | F1: product_id | G1: product_name | H1: size | I1: category
F2: 1 | G2: Nestle Water Pure Life | H2: 500 ml | I2: water
F3: 2 | G3: Nestle Water Pure Life | H3: 1500 ml | I3: water
F4: 3 | G4: Nestle Water Pure Life | H4: 5 Litre | I4: water
F5: 4 | G5: Nestle Water Pure Life | H5: 19 Litre | I5: water

Sheet Purchase Order
A1: timestamp | B1: product_id | C1: product_name | D1: size | E1: category | F1: qty_order

Sheet Stock Received
A1: timestamp | B1: product_id | C1: product_name | D1: size | E1: category | F1: qty_recieved | G1: cost_price | H1: total_cost | I1: expiry_date | J1: expairy_days_remaining
A2: 18-11-2025 | B2: 1 | C2: Nestle Water Pure Life | D2: 500 ml | E2: water | F2: 1000 | G2: 50 | H2: =G2*F2 -> 50000 | I2: 18-11-2026 | J2: =DATE(RIGHT(I2,4), MID(I2,4,2), LEFT(I2,2)) - TODAY() -> 363
A3: 18-11-2025 | B3: 2 | C3: Nestle Water Pure Life | D3: 1500 ml | E3: water | F3: 1000 | G3: 100 | H3: =G3*F3 -> 100000 | I3: 18-11-2026 | J3: =DATE(RIGHT(I3,4), MID(I3,4,2), LEFT(I3,2)) - TODAY() -> 363
A4: 18-11-2025 | B4: 3 | C4: Nestle Water Pure Life | D4: 5 Litre | E4: water | F4: 1000 | G4: 200 | H4: =G4*F4 -> 200000 | I4: 18-11-2026 | J4: =DATE(RIGHT(I4,4), MID(I4,4,2), LEFT(I4,2)) - TODAY() -> 363
A5: 18-11-2025 | B5: 4 | C5: Nestle Water Pure Life | D5: 19 Litre | E5: water | F5: 1000 | G5: 500 | H5: =G5*F5 -> 500000 | I5: 18-11-2026 | J5: =DATE(RIGHT(I5,4), MID(I5,4,2), LEFT(I5,2)) - TODAY() -> 363

Sheet Purchase Register
A1: Sr | B1: product_id | C1: product_name | D1: size | E1: category | F1: qty_received | G1: cost_price_per_unit | H1: sale_price_per_unit | I1: total_cost
A2: 1 | B2: 1 | C2: Nestle Water Pure Life | D2: 500 ml | E2: water | F2: =SUMIF('Stock Received'!B:B, B2, 'Stock Received'!F:F) -> 1000 | G2: 50 | H2: 100 | I2: =F2*G2 -> 50000
A3: 2 | B3: 2 | C3: Nestle Water Pure Life | D3: 1500 ml | E3: water | F3: =SUMIF('Stock Received'!B:B, B3, 'Stock Received'!F:F) -> 1000 | G3: 100 | H3: 200 | I3: =F3*G3 -> 100000
A4: 3 | B4: 3 | C4: Nestle Water Pure Life | D4: 5 Litre | E4: water | F4: =SUMIF('Stock Received'!B:B, B4, 'Stock Received'!F:F) -> 1000 | G4: 200 | H4: 400 | I4: =F4*G4 -> 200000
A5: 4 | B5: 4 | C5: Nestle Water Pure Life | D5: 19 Litre | E5: water | F5: =SUMIF('Stock Received'!B:B, B5, 'Stock Received'!F:F) -> 1000 | G5: 500 | H5: 1000 | I5: =F5*G5 -> 500000

Sheet Customer Order
A1: timestamp | B1: product_id | C1: product_name | D1: size | E1: category | F1: quntity | G1: price | H1: total_price | I1: order_id | J1: customer_name | K1: whatsapp_number | L1: email | M1: address | N1: landmark | O1: payment_method | P1: delivery_time_preference | Q1: status | R1: description
A2: 2025-11-20T01:35:39.777Z | B2: 1 | C2: Nestle Water Pure Life | D2: 500 ml | E2: water | F2: 501 | G2: 100 | H2: 50100 | I2: Ord-1763602539782 | J2: Faisal Mehmood | K2: 9231111111 | L2: shahfaisal1234@gmail.com | M2: Usman Abad Colony Multan | N2: Eid Gha Mosque | O2: Cash on Delivery | P2: Afternoon | Q2: Confirmed | R2: Order accepted (in stock)

Sheet Invoice
A1: invoice no | B1: date | C1: customer_name | D1: whatsapp_no | E1: address | F1: product_name | G1: size | H1: quntity | I1: price | J1: total_amount | K1: status
A2: INV-1763602571457 | B2: 2025-11-19T00:00:00.000-05:00 | C2: Faisal Mehmood | D2: 9231111111 | E2: Usman Abad Colony Multan | F2: Nestle Water Pure Life | G2: 500 ml | H2: 501 | I2: 100 | J2: 50100

Sheet Sales Register
A1: sr # | B1: product_id | C1: product_name | D1: size | E1: category | F1: sale | G1: sale_price | H1: total_sale
A2: 1 | B2: 1 | C2: =VLOOKUP(B2, 'Purchase Register'!B:F, 2, FALSE) -> Nestle Water Pure Life | D2: =VLOOKUP(B2, 'Purchase Register'!B:F, 3, FALSE) -> 500 ml | E2: =VLOOKUP(B2, 'Purchase Register'!B:H, 4, FALSE) -> water | F2: =SUMIF('Customer Order'!B:B, B2, 'Customer Order'!F:F) -> 501 | G2: ='Purchase Register'!H2 -> 100 | H2: =G2*F2 -> 50100
A3: 2 | B3: 2 | C3: =VLOOKUP(B3, 'Purchase Register'!B:F, 2, FALSE) -> Nestle Water Pure Life | D3: =VLOOKUP(B3, 'Purchase Register'!B:F, 3, FALSE) -> 1500 ml | E3: =VLOOKUP(B3, 'Purchase Register'!B:H, 4, FALSE) -> water | F3: =SUMIF('Customer Order'!B:B, B3, 'Customer Order'!F:F) -> 0 | G3: ='Purchase Register'!H3 -> 200 | H3: =G3*F3 -> 0
A4: 3 | B4: 3 | C4: =VLOOKUP(B4, 'Purchase Register'!B:F, 2, FALSE) -> Nestle Water Pure Life | D4: =VLOOKUP(B4, 'Purchase Register'!B:F, 3, FALSE) -> 5 Litre | E4: =VLOOKUP(B4, 'Purchase Register'!B:H, 4, FALSE) -> water | F4: =SUMIF('Customer Order'!B:B, B4, 'Customer Order'!F:F) -> 0 | G4: ='Purchase Register'!H4 -> 400 | H4: =G4*F4 -> 0
A5: 4 | B5: 4 | C5: =VLOOKUP(B5, 'Purchase Register'!B:F, 2, FALSE) -> Nestle Water Pure Life | D5: =VLOOKUP(B5, 'Purchase Register'!B:F, 3, FALSE) -> 19 Litre | E5: =VLOOKUP(B5, 'Purchase Register'!B:H, 4, FALSE) -> water | F5: =SUMIF('Customer Order'!B:B, B5, 'Customer Order'!F:F) -> 0 | G5: ='Purchase Register'!H5 -> 1000 | H5: =G5*F5 -> 0

Sheet Stock Register
A1: product_id | B1: product_name | C1: size | D1: category | E1: purchase_stock | F1: sale_stock | G1: current_stock | H1: cost_price | I1: sale_price | J1: total_purchase | K1: total_sale | L1: status | M1: reorder_level | N1: need_to_reorder
A2: 1 | B2: =VLOOKUP(A2, 'Purchase Register'!B:E, 2, FALSE) -> Nestle Water Pure Life | C2: =VLOOKUP(A2, 'Purchase Register'!B:E, 3, FALSE) -> 500 ml | D2: =VLOOKUP(B2, 'Purchase Register'!C:F, 3, FALSE) -> water | E2: =VLOOKUP(C2, 'Purchase Register'!D:G, 3, FALSE) -> 1000 | F2: =VLOOKUP(A2, 'Sales Register'!A:G, 6, FALSE) -> 501 | G2: =E2-F2 -> 499 | H2: =VLOOKUP(A2, 'Purchase Register'!B:I, 6, FALSE) -> 50 | I2: =VLOOKUP(A2, 'Purchase Register'!B:I, 7, FALSE) -> 100 | J2: =E2*H2 -> 50000 | K2: =F2*I2 -> 50100 | L2: =IF(G2=0,"Not Available",IF(G2<=10,"Low Stock","Available")) -> Available | M2: 500 | N2: =IF(G2<=M2,"Yes","No") -> Yes
A3: 2 | B3: =VLOOKUP(A3, 'Purchase Register'!B:E, 2, FALSE) -> Nestle Water Pure Life | C3: =VLOOKUP(A3, 'Purchase Register'!B:E, 3, FALSE) -> 1500 ml | D3: =VLOOKUP(B3, 'Purchase Register'!C:F, 3, FALSE) -> water | E3: =VLOOKUP(C3, 'Purchase Register'!D:G, 3, FALSE) -> 1000 | F3: =VLOOKUP(A3, 'Sales Register'!A:G, 6, FALSE) -> 0 | G3: =E3-F3 -> 1000 | H3: =VLOOKUP(A3, 'Purchase Register'!B:I, 6, FALSE) -> 100 | I3: =VLOOKUP(A3, 'Purchase Register'!B:I, 7, FALSE) -> 200 | J3: =E3*H3 -> 100000 | K3: =F3*I3 -> 0 | L3: =IF(G3=0,"Not Available",IF(G3<=10,"Low Stock","Available")) -> Available | M3: 500 | N3: =IF(G3<=M3,"Yes","No") -> No
A4: 3 | B4: =VLOOKUP(A4, 'Purchase Register'!B:E, 2, FALSE) -> Nestle Water Pure Life | C4: =VLOOKUP(A4, 'Purchase Register'!B:E, 3, FALSE) -> 5 Litre | D4: =VLOOKUP(B4, 'Purchase Register'!C:F, 3, FALSE) -> water | E4: =VLOOKUP(C4, 'Purchase Register'!D:G, 3, FALSE) -> 1000 | F4: =VLOOKUP(A4, 'Sales Register'!A:G, 6, FALSE) -> 0 | G4: =E4-F4 -> 1000 | H4: =VLOOKUP(A4, 'Purchase Register'!B:I, 6, FALSE) -> 200 | I4: =VLOOKUP(A4, 'Purchase Register'!B:I, 7, FALSE) -> 400 | J4: =E4*H4 -> 200000 | K4: =F4*I4 -> 0 | L4: =IF(G4=0,"Not Available",IF(G4<=10,"Low Stock","Available")) -> Available | M4: 500 | N4: =IF(G4<=M4,"Yes","No") -> No
A5: 4 | B5: =VLOOKUP(A5, 'Purchase Register'!B:E, 2, FALSE) -> Nestle Water Pure Life | C5: =VLOOKUP(A5, 'Purchase Register'!B:E, 3, FALSE) -> 19 Litre | D5: =VLOOKUP(B5, 'Purchase Register'!C:F, 3, FALSE) -> water | E5: =VLOOKUP(C5, 'Purchase Register'!D:G, 3, FALSE) -> 1000 | F5: =VLOOKUP(A5, 'Sales Register'!A:G, 6, FALSE) -> 0 | G5: =E5-F5 -> 1000 | H5: =VLOOKUP(A5, 'Purchase Register'!B:I, 6, FALSE) -> 500 | I5: =VLOOKUP(A5, 'Purchase Register'!B:I, 7, FALSE) -> 1000 | J5: =E5*H5 -> 500000 | K5: =F5*I5 -> 0 | L5: =IF(G5=0,"Not Available",IF(G5<=10,"Low Stock","Available")) -> Available | M5: 500 | N5: =IF(G5<=M5,"Yes","No") -> No
